reachy_sdk/__init__.py
reachy_sdk/arm.py
reachy_sdk/camera.py
reachy_sdk/device_holder.py
reachy_sdk/fan.py
reachy_sdk/force_sensor.py
reachy_sdk/head.py
reachy_sdk/joint.py
reachy_sdk/reachy_sdk.py
reachy_sdk/register.py
reachy_sdk/trajectory/__init__.py
reachy_sdk/trajectory/interpolation.py
reachy_sdk-0.7.0.dist-info/LICENSE
reachy_sdk-0.7.0.dist-info/METADATA
reachy_sdk-0.7.0.dist-info/WHEEL
reachy_sdk-0.7.0.dist-info/top_level.txt
reachy_sdk-0.7.0.dist-info/RECORD
