Metadata-Version: 2.1
Name: reachy-sdk
Version: 0.7.0
Summary: Python Reachy SDK.
Home-page: https://github.com/pollen-robotics/reachy-sdk
Author: Pollen Robotics
Author-email: contact@pollen-robotics.com
License-File: LICENSE
Requires-Dist: numpy
Requires-Dist: opencv-python
Requires-Dist: reachy-sdk-api (>=0.7.0)
Requires-Dist: grpcio (>=1.37)
Requires-Dist: protobuf (>3)
Requires-Dist: pyquaternion
Requires-Dist: scipy
Requires-Dist: mobile-base-sdk
Provides-Extra: doc
Requires-Dist: sphinx ; extra == 'doc'
